psmpy/__init__.py
psmpy/functions.py
psmpy/plotting.py
psmpy/psmpy.py
psmpy-0.3.16.dist-info/licenses/LICENSE.txt
psmpy-0.3.16.dist-info/METADATA
psmpy-0.3.16.dist-info/WHEEL
psmpy-0.3.16.dist-info/top_level.txt
psmpy-0.3.16.dist-info/RECORD
