Metadata-Version: 2.4
Name: psmpy
Version: 0.3.16
Summary: Propensity score matching for python and graphical plots
Author-email: Adrienne Kline <askline1@gmail.com>
Project-URL: Issues, https://github.com/adriennekline/psmpy/issues
Project-URL: Homepage, https://github.com/adriennekline/psmpy
Project-URL: Documentation, https://pypi.org/project/psmpy
Keywords: propensity score matching,statistics,plotting
Classifier: Programming Language :: Python :: 3
Classifier: License :: OSI Approved :: MIT License
Classifier: Intended Audience :: Science/Research
Classifier: Operating System :: OS Independent
License-File: LICENSE.txt
Requires-Dist: matplotlib
Requires-Dist: numpy
Requires-Dist: pandas
Requires-Dist: seaborn
Requires-Dist: scikit-learn
Requires-Dist: scipy
Dynamic: license-file
